say/__init__.py
say/__main__.py
say/main.py
say/TTS/__init__.py
say/TTS/as_client.py
say/TTS/as_service.py
say/TTS/audio.py
say/TTS/engine.py
say/TTS/exception.py
say/TTS/utils.py
say/entry_points/__init__.py
say/entry_points/run_say.py
tts_say-2.4.1.dist-info/LICENSE
tts_say-2.4.1.dist-info/METADATA
tts_say-2.4.1.dist-info/WHEEL
tts_say-2.4.1.dist-info/entry_points.txt
tts_say-2.4.1.dist-info/top_level.txt
tts_say-2.4.1.dist-info/RECORD
