Metadata-Version: 2.1
Name: tts-say
Version: 2.4.1
Summary: echo but with TTS.
Home-page: https://gitlab.com/waser-technologies/technologies/say
Author: Danny Waser
Author-email: danny@waser.tech
Project-URL: Documentation, https://gitlab.com/waser-technologies/technologies/say/blob/main/README.md
Project-URL: Code, https://gitlab.com/waser-technologies/technologies/say
Project-URL: Issue tracker, https://gitlab.com/waser-technologies/technologies/say/issues
Classifier: Programming Language :: Python :: 3
Classifier: Programming Language :: Python :: 3.7
Classifier: Programming Language :: Python :: 3.8
Classifier: Programming Language :: Python :: 3.9
Classifier: Programming Language :: Python :: 3.10
Classifier: Programming Language :: Python :: 3.11
Classifier: License :: OSI Approved :: MIT License
Classifier: Operating System :: OS Independent
Requires-Python: >=3.7,<3.12
License-File: LICENSE
Requires-Dist: TTS
Requires-Dist: python-shell
Requires-Dist: simpleaudio
Requires-Dist: pydub
Requires-Dist: num2words
Requires-Dist: websockets
Requires-Dist: sanic
Requires-Dist: toml
